SoC-LED-Clock/SoC-LED-Clock.srcs/sources_1/new/font_rom.v
`timescale 1ns / 1ps
//////////////////////////////////////////////////////////////////////////////////
// Company: 
// Engineer: 
// 
// Create Date: 06/15/2026 08:59:07 PM
// Design Name: 
// Module Name: font_rom
// Project Name: 
// Target Devices: 
// Tool Versions: 
// Description: 
// 
// Dependencies: 
// 
// Revision:
// Revision 0.01 - File Created
// Additional Comments:
// 
//////////////////////////////////////////////////////////////////////////////////
module font_rom (
    input clk,
    input      [6:0] ascii_code,
    input      [2:0] row_index,
    output reg [7:0] row_data
);

    reg [63:0] full_char;

    // Map ASCII codes to 64-bit character bitmaps (8x8 grid)
    always @(*) begin
        case (ascii_code)
            // Numbers (0x30 - 0x39)
            7'h30: full_char = 64'h003C666E76663C00; // 0
            7'h31: full_char = 64'h0018381818183C00; // 1
            7'h32: full_char = 64'h003C66060C30607E; // 2
            7'h33: full_char = 64'h003C66061C06663C; // 3
            7'h34: full_char = 64'h000C1C2C4C7E0C0C; // 4
            7'h35: full_char = 64'h007E607C0606663C; // 5
            7'h36: full_char = 64'h003C607C6666663C; // 6
            7'h37: full_char = 64'h007E060C10202020; // 7
            7'h38: full_char = 64'h003C66663C66663C; // 8
            7'h39: full_char = 64'h003C66663E060C38; // 9

            // Symbols
            7'h3A: full_char = 64'h0000181800181800; // :

            // Lowercase English Letters (0x61 - 0x7A)
            7'h61: full_char = 64'h00003C063E663A00; // a
            7'h62: full_char = 64'h60607C6666667C00; // b
            7'h63: full_char = 64'h00003C6260623C00; // c
            7'h64: full_char = 64'h06063E6666663E00; // d
            7'h65: full_char = 64'h00003C667E603C00; // e
            7'h66: full_char = 64'h1C24207C20202000; // f
            7'h67: full_char = 64'h00003E66663E063C; // g
            7'h68: full_char = 64'h60607C6666666600; // h
            7'h69: full_char = 64'h1800181818183C00; // i
            7'h6A: full_char = 64'h0C000C0C0C0C3C1C; // j
            7'h6B: full_char = 64'h6060666C786C6600; // k
            7'h6C: full_char = 64'h3010101010101E00; // l
            7'h6D: full_char = 64'h00006C5656565600; // m
            7'h6E: full_char = 64'h0000786464646400; // n
            7'h6F: full_char = 64'h00003C6666663C00; // o
            7'h70: full_char = 64'h00007C66667C6060; // p
            7'h71: full_char = 64'h00003E66663E0606; // q
            7'h72: full_char = 64'h00006C7260606000; // r
            7'h73: full_char = 64'h00003C603C063C00; // s
            7'h74: full_char = 64'h00107C1010100C00; // t
            7'h75: full_char = 64'h0000666666663E00; // u
            7'h76: full_char = 64'h00006666663C1800; // v
            7'h77: full_char = 64'h000066666E7E3600; // w
            7'h78: full_char = 64'h0000663C183C6600; // x
            7'h79: full_char = 64'h000066663E063C30; // y
            7'h7A: full_char = 64'h00007E0C18307E00; // z

            default: full_char = 64'h0000000000000000; // Space / Blank
        endcase
    end

    // Extract the requested 8-bit row slice from the 64-bit configuration
    always @(posedge clk) begin
        case (row_index)
            3'd0: row_data <= full_char[63:56];
            3'd1: row_data <= full_char[55:48];
            3'd2: row_data <= full_char[47:40];
            3'd3: row_data <= full_char[39:32];
            3'd4: row_data <= full_char[31:24];
            3'd5: row_data <= full_char[23:16];
            3'd6: row_data <= full_char[15:8];
            3'd7: row_data <= full_char[7:0];
            default: row_data <= 8'b00000000;
        endcase
    end

endmodule

SoC-LED-Clock/SoC-LED-Clock.srcs/sources_1/new/translator.v
`timescale 1ns / 1ps
//////////////////////////////////////////////////////////////////////////////////
// Company: 
// Engineer: 
// 
// Create Date: 06/15/2026 08:49:38 PM
// Design Name: 
// Module Name: translator
// Project Name: 
// Target Devices: 
// Tool Versions: 
// Description: 
// 
// Dependencies: 
// 
// Revision:
// Revision 0.01 - File Created
// Additional Comments:
// 
//////////////////////////////////////////////////////////////////////////////////
module translator #(
    parameter N = 4 // Number of modules
)(
    input             clk,
    input             start,
    input [N-1:0][6:0] ascii_data,   // 7 bits per character * N modules
    input [2:0]       row_idx,
    
    output reg [(16*N)-1:0] row_packet,   // 16-bit packet to send to SPI engine
    output reg        packet_valid, // Tells SPI engine to transmit
    output reg        ready
);

    // State Machine Encodings
    localparam IDLE     = 3'd0;
    localparam FETCH    = 3'd1;
    localparam DONE     = 3'd2;
    localparam WAIT_ROM = 3'd3;
    localparam STORE    = 3'd4;

    reg [2:0] state       = IDLE;
    reg [6:0] ascii_code  = 7'b0;
    reg [$clog2(N):0] idx = 0;
    wire [7:0] row_data;

    // Instantiate Font ROM
    font_rom ascii_rom (
        .clk(clk),
        .ascii_code(ascii_code),
        .row_index(row_idx),
        .row_data(row_data)
    );

    always @(posedge clk) begin
        case (state)
            IDLE: begin
                ready        <= 1'b1;
                packet_valid <= 1'b0;
                ascii_code   <= 7'b0;
                idx          <= 1'b0;
                
                if (start) begin
                    ready <= 1'b0;
                    state <= FETCH;
                end
            end

            FETCH: begin
                ascii_code   <= ascii_data[idx];
                state        <= WAIT_ROM;
            end
            
            WAIT_ROM: begin
                state <= STORE;
            end
            
            STORE: begin
                row_packet[(N-1-idx)*16+:16] <= {4'b0000, row_idx, row_data};
                idx <= idx + 1'b1;   
                state <= (idx == N-1) ? DONE : FETCH;
                if (idx == N-1) begin
                    state <= DONE;
                    idx <= 0;
                end else begin
                    idx <= idx + 1;
                    state <= FETCH;
                end
            end

            DONE: begin
                ready        <= 1'b1;
                packet_valid <= 1'b1;
                state        <= IDLE;
            end
            
            default: state <= IDLE;
        endcase
    end
endmodule

TESTBENCH/benches/tb_translator.v
module tb_translator;

reg clk;
reg start;
reg [27:0] ascii_data;
reg [2:0] row_idx;

wire [63:0] row_packet;
wire packet_valid;
wire ready;

// reg [6:0] ascii_code;
// wire [7:0] row_data;

translator #(
    .N(4)
) UUT (
    .clk(clk),
    .start(start),
    .row_idx(row_idx),
    .ascii_data(ascii_data),
    .row_packet(row_packet),
    .packet_valid(packet_valid),
    .ready(ready)
);

// font_rom UUT_rom(
//     .clk(clk),
//     .ascii_code(ascii_code),
//     .row_index(row_index),
//     .row_data(row_data)
// );

// Clock generator: flips state every 5ns (10ns period)
always #5 clk = ~clk;

initial begin
    $dumpfile("TESTBENCH/sims/trans.vcd");
    // $dumpvars(0, tb_rom);
    $dumpvars(0, tb_translator);

    clk = 0; 
    ascii_data = {7'h63, 7'h68, 7'h75, 7'h6A};
    start = 0;
    row_idx = 0;

    #10 start = 1;

    repeat(40) begin
        @(posedge clk);
    end

    #20 $finish;
end

// initial begin
//     $monitor("Time=%0t | Row=%d | Data=%h", $time, row_index, row_data);
// end
always @(posedge clk) begin
    $display("Time=%0t | State=%d | idx=%d | row_packet=%h", $time, UUT.state, UUT.idx, row_packet);
end

endmodule

TESTBENCH/sims/trans.vcd
$date
	Tue Jun 16 14:13:38 2026
$end
$version
	Icarus Verilog
$end
$timescale
	1ps
$end
$scope module tb_translator $end
$var wire 64 ! row_packet [63:0] $end
$var wire 1 " ready $end
$var wire 1 # packet_valid $end
$var reg 28 $ ascii_data [27:0] $end
$var reg 1 % clk $end
$var reg 3 & row_idx [2:0] $end
$var reg 1 ' start $end
$scope module UUT $end
$var wire 28 ( ascii_data [27:0] $end
$var wire 1 % clk $end
$var wire 3 ) row_idx [2:0] $end
$var wire 1 ' start $end
$var wire 8 * row_data [7:0] $end
$var parameter 3 + DONE $end
$var parameter 3 , FETCH $end
$var parameter 3 - IDLE $end
$var parameter 32 . N $end
$var parameter 3 / STORE $end
$var parameter 3 0 WAIT_ROM $end
$var reg 7 1 ascii_code [6:0] $end
$var reg 3 2 idx [2:0] $end
$var reg 1 # packet_valid $end
$var reg 1 " ready $end
$var reg 64 3 row_packet [63:0] $end
$var reg 3 4 state [2:0] $end
$scope module ascii_rom $end
$var wire 7 5 ascii_code [6:0] $end
$var wire 1 % clk $end
$var wire 3 6 row_index [2:0] $end
$var reg 64 7 full_char [63:0] $end
$var reg 8 8 row_data [7:0] $end
$upscope $end
$upscope $end
$upscope $end
$enddefinitions $end
$comment Show the parameter values. $end
$dumpall
b11 0
b100 /
b100 .
b0 -
b1 ,
b10 +
$end
#0
$dumpvars
bx 8
b0 7
b0 6
b0 5
b0 4
bx 3
b0 2
b0 1
bx *
b0 )
b1100011110100011101011101010 (
0'
b0 &
0%
b1100011110100011101011101010 $
x#
x"
bx !
$end
#5000
b0 *
b0 8
0#
1"
1%
#10000
0%
1'
#15000
b1 4
0"
1%
#20000
0%
#25000
b110000000000000011000000110000001100000011000011110000011100 7
b11 4
b1101010 1
b1101010 5
1%
#30000
0%
#35000
b100 4
b1100 *
b1100 8
1%
#40000
0%
#45000
b1 4
b1 2
b1100xxxxxxxxxxxxxxxxxxxxxxxxxxxxxxxxxxxxxxxxxxxxxxxx !
b1100xxxxxxxxxxxxxxxxxxxxxxxxxxxxxxxxxxxxxxxxxxxxxxxx 3
1%
#50000
0%
#55000
b11001100110011001100110011001100011111000000000 7
b11 4
b1110101 1
b1110101 5
1%
#60000
0%
#65000
b0 *
b0 8
b100 4
1%
#70000
0%
#75000
b1 4
b10 2
b11000000000000000000xxxxxxxxxxxxxxxxxxxxxxxxxxxxxxxx !
b11000000000000000000xxxxxxxxxxxxxxxxxxxxxxxxxxxxxxxx 3
1%
#80000
0%
#85000
b110000001100000011111000110011001100110011001100110011000000000 7
b11 4
b1101000 1
b1101000 5
1%
#90000
0%
#95000
b100 4
b1100000 *
b1100000 8
1%
#100000
0%
#105000
b1 4
b11 2
b110000000000000000000000000001100000xxxxxxxxxxxxxxxx !
b110000000000000000000000000001100000xxxxxxxxxxxxxxxx 3
1%
#110000
0%
#115000
b1111000110001001100000011000100011110000000000 7
b11 4
b1100011 1
b1100011 5
1%
#120000
0%
#125000
b0 *
b0 8
b100 4
1%
#130000
0%
#135000
b10 4
b0 2
b1100000000000000000000000000011000000000000000000000 !
b1100000000000000000000000000011000000000000000000000 3
1%
#140000
0%
#145000
b0 4
1#
1"
1%
#150000
0%
#155000
b0 7
b1 4
0"
b0 1
b0 5
0#
1%
#160000
0%
#165000
b110000000000000011000000110000001100000011000011110000011100 7
b11 4
b1101010 1
b1101010 5
1%
#170000
0%
#175000
b100 4
b1100 *
b1100 8
1%
#180000
0%
#185000
b1 4
b1 2
1%
#190000
0%
#195000
b11001100110011001100110011001100011111000000000 7
b11 4
b1110101 1
b1110101 5
1%
#200000
0%
#205000
b0 *
b0 8
b100 4
1%
#210000
0%
#215000
b1 4
b10 2
1%
#220000
0%
#225000
b110000001100000011111000110011001100110011001100110011000000000 7
b11 4
b1101000 1
b1101000 5
1%
#230000
0%
#235000
b100 4
b1100000 *
b1100000 8
1%
#240000
0%
#245000
b1 4
b11 2
1%
#250000
0%
#255000
b1111000110001001100000011000100011110000000000 7
b11 4
b1100011 1
b1100011 5
1%
#260000
0%
#265000
b0 *
b0 8
b100 4
1%
#270000
0%
#275000
b10 4
b0 2
1%
#280000
0%
#285000
b0 4
1#
1"
1%
#290000
0%
#295000
b0 7
b1 4
0"
b0 1
b0 5
0#
1%
#300000
0%
#305000
b110000000000000011000000110000001100000011000011110000011100 7
b11 4
b1101010 1
b1101010 5
1%
#310000
0%
#315000
b100 4
b1100 *
b1100 8
1%
#320000
0%
#325000
b1 4
b1 2
1%
#330000
0%
#335000
b11001100110011001100110011001100011111000000000 7
b11 4
b1110101 1
b1110101 5
1%
#340000
0%
#345000
b0 *
b0 8
b100 4
1%
#350000
0%
#355000
b1 4
b10 2
1%
#360000
0%
#365000
b110000001100000011111000110011001100110011001100110011000000000 7
b11 4
b1101000 1
b1101000 5
1%
#370000
0%
#375000
b100 4
b1100000 *
b1100000 8
1%
#380000
0%
#385000
b1 4
b11 2
1%
#390000
0%
#395000
b1111000110001001100000011000100011110000000000 7
b11 4
b1100011 1
b1100011 5
1%
#400000
0%
#405000
b0 *
b0 8
b100 4
1%
#410000
0%
#415000
b10 4
b0 2
1%
#420000
0%
#425000
b0 4
1#
1"
1%
